convertbng/__init__.py
convertbng/convertbng_p.pxd
convertbng/cutil.cpython-313-x86_64-linux-gnu.so
convertbng/cutil.pyx
convertbng/header.h
convertbng/liblonlat_bng.so
convertbng/stdbool.h
convertbng/util.py
convertbng-0.7.10.dist-info/METADATA
convertbng-0.7.10.dist-info/WHEEL
convertbng-0.7.10.dist-info/RECORD
convertbng-0.7.10.dist-info/licenses/LICENSE.md
