Metadata-Version: 2.4
Name: convertbng
Version: 0.7.10
Summary: Fast lon, lat to and from ETRS89 and BNG (OSGB36) using the OS OSTN15 transform via Rust FFI
Keywords: Geo,OSTN02,OSTN15,BNG,OSGB36,GIS
Author-Email: =?utf-8?q?Stephan_H=C3=BCgel?= <urschrei@gmail.com>
License-Expression: BlueOak-1.0.0
License-File: LICENSE.md
Classifier: Programming Language :: Python
Classifier: Programming Language :: Python :: 3.10
Classifier: Programming Language :: Python :: 3.11
Classifier: Programming Language :: Python :: 3.12
Classifier: Programming Language :: Python :: 3.13
Classifier: Programming Language :: Python :: 3.14
Classifier: Development Status :: 5 - Production/Stable
Classifier: Intended Audience :: Developers
Classifier: Intended Audience :: Science/Research
Classifier: Intended Audience :: Education
Classifier: Operating System :: OS Independent
Classifier: Topic :: Software Development :: Libraries :: Python Modules
Classifier: Topic :: Scientific/Engineering :: GIS
Project-URL: Repository, https://github.com/urschrei/convertbng
Project-URL: Tracker, https://github.com/urschrei/convertbng/issues
Requires-Python: >=3.10
Requires-Dist: numpy>=2.0.0
